{"cameraMode":{"drawMode":0,"name":"Shaded","section":"Shading Mode"},"sceneLighting":true,"audioPlay":false,"sceneViewState":{"showFog":true,"showMaterialUpdate":false,"showSkybox":true,"showFlares":true,"showImageEffects":true,"showParticleSystems":true},"in2DMode":false,"pivot":{"x":1.9487076997756959,"y":0.8012449741363525,"z":0.8426226377487183},"rotation":{"x":-0.380569726228714,"y":0.2984502613544464,"z":-0.1312369555234909,"w":-0.8653861880302429},"size":16.197370529174806,"orthographic":false}